linty_fresh/__init__.py
linty_fresh/main.py
linty_fresh/problem.py
linty_fresh/linters/__init__.py
linty_fresh/linters/checkstyle.py
linty_fresh/linters/mypy.py
linty_fresh/linters/pylint.py
linty_fresh/linters/swiftlint.py
linty_fresh/reporters/__init__.py
linty_fresh/reporters/github_reporter.py
linty_fresh/storage/__init__.py
linty_fresh/storage/git_storage_engine.py
linty_fresh_py34-0.2.1.post6.dist-info/DESCRIPTION.rst
linty_fresh_py34-0.2.1.post6.dist-info/METADATA
linty_fresh_py34-0.2.1.post6.dist-info/RECORD
linty_fresh_py34-0.2.1.post6.dist-info/WHEEL
linty_fresh_py34-0.2.1.post6.dist-info/entry_points.txt
linty_fresh_py34-0.2.1.post6.dist-info/metadata.json
linty_fresh_py34-0.2.1.post6.dist-info/top_level.txt
