Metadata-Version: 2.0
Name: linty-fresh-py34
Version: 0.2.1.post6
Summary: 
Home-page: https://github.com/twidi/linty-fresh
Author: Roy Williams
Author-email: rwilliams@lyft.com
License: apache
Platform: UNKNOWN
Classifier: Environment :: Console
Classifier: Intended Audience :: Developers
Classifier: License :: OSI Approved :: Apache Software License
Classifier: Programming Language :: Python
Classifier: Programming Language :: Python :: 3
Classifier: Topic :: Software Development :: Quality Assurance
Requires-Dist: aiohttp (>=0.19.0)
Requires-Dist: typing (>=3.5.0.1)
